LICENSE.md
MANIFEST.in
README.md
setup.cfg
setup.py
jupyter_kernel_gateway_quarc_custom.egg-info/PKG-INFO
jupyter_kernel_gateway_quarc_custom.egg-info/SOURCES.txt
jupyter_kernel_gateway_quarc_custom.egg-info/dependency_links.txt
jupyter_kernel_gateway_quarc_custom.egg-info/entry_points.txt
jupyter_kernel_gateway_quarc_custom.egg-info/requires.txt
jupyter_kernel_gateway_quarc_custom.egg-info/top_level.txt
kernel_gateway/__init__.py
kernel_gateway/__main__.py
kernel_gateway/_version.py
kernel_gateway/gatewayapp.py
kernel_gateway/mixins.py
kernel_gateway/base/__init__.py
kernel_gateway/base/handlers.py
kernel_gateway/jupyter_websocket/__init__.py
kernel_gateway/jupyter_websocket/handlers.py
kernel_gateway/jupyter_websocket/swagger.json
kernel_gateway/jupyter_websocket/swagger.yaml
kernel_gateway/notebook_http/__init__.py
kernel_gateway/notebook_http/errors.py
kernel_gateway/notebook_http/handlers.py
kernel_gateway/notebook_http/request_utils.py
kernel_gateway/notebook_http/cell/__init__.py
kernel_gateway/notebook_http/cell/parser.py
kernel_gateway/notebook_http/swagger/__init__.py
kernel_gateway/notebook_http/swagger/builders.py
kernel_gateway/notebook_http/swagger/handlers.py
kernel_gateway/notebook_http/swagger/parser.py
kernel_gateway/services/__init__.py
kernel_gateway/services/kernels/__init__.py
kernel_gateway/services/kernels/handlers.py
kernel_gateway/services/kernels/manager.py
kernel_gateway/services/kernels/pool.py
kernel_gateway/services/kernelspecs/__init__.py
kernel_gateway/services/kernelspecs/handlers.py
kernel_gateway/services/sessions/__init__.py
kernel_gateway/services/sessions/handlers.py
kernel_gateway/services/sessions/sessionmanager.py