Metadata-Version: 1.1
Name: jupyter-kernel-gateway-quarc-custom
Version: 2.0.0.dev0
Summary: A web server for spawning and communicating with Jupyter kernels
Home-page: http://github.com/jupyter-incubator/kernel_gateway
Author: Jupyter Development Team
Author-email: jupyter@googlegroups.com
License: BSD
Keywords: Interactive,Interpreter,Kernel,Web,Cloud
Platform: Linux
Platform: Mac OS X
Platform: Windows
Classifier: Intended Audience :: Developers
Classifier: Intended Audience :: System Administrators
Classifier: Intended Audience :: Science/Research
Classifier: License :: OSI Approved :: BSD License
Classifier: Programming Language :: Python
Classifier: Programming Language :: Python :: 2
Classifier: Programming Language :: Python :: 3
